quyckplot/DataSet.py
quyckplot/Plotter.py
quyckplot/__init__.py
quyckplot/utils.py
quyckplot-0.0.3.dist-info/METADATA
quyckplot-0.0.3.dist-info/WHEEL
quyckplot-0.0.3.dist-info/top_level.txt
quyckplot-0.0.3.dist-info/RECORD
