Metadata-Version: 2.1
Name: quyckplot
Version: 0.0.3
Summary: A package that helps the process of loading multiple files and plotting the data inside.
Author: Takanori Akieda
Author-email: <takanori.codron@gmail.com>
Keywords: python,data analysis,scientific
Classifier: Programming Language :: Python :: 3
Classifier: Operating System :: Unix
Classifier: Operating System :: MacOS :: MacOS X
Classifier: Operating System :: Microsoft :: Windows
Requires-Dist: numpy
Requires-Dist: scipy
Requires-Dist: matplotlib
Requires-Dist: pandas
